setup.py
proso/__init__.py
proso/models/__init__.py
proso/models/environment.py
proso/models/metric.py
proso/models/optimize.py
proso/models/prediction.py
proso/models/recommendation.py
proso/models/test_environment.py
proso_model.egg-info/PKG-INFO
proso_model.egg-info/SOURCES.txt
proso_model.egg-info/dependency_links.txt
proso_model.egg-info/namespace_packages.txt
proso_model.egg-info/requires.txt
proso_model.egg-info/top_level.txt