Metadata-Version: 1.0
Name: proso-model
Version: 1.0.0
Summary: Models library for PROSO project
Home-page: https://github.com/proso/geography-model-libs/
Author: Jan Papousek
Author-email: jan.papousek@gmail.com
License: Gnu GPL v3
Platform: UNKNOWN
